yelp/__init__.py
yelp/client.py
yelp/config.py
yelp/errors.py
yelp/oauth1_authenticator.py
yelp/endpoint/__init__.py
yelp/endpoint/business.py
yelp/endpoint/phone_search.py
yelp/endpoint/search.py
yelp/obj/__init__.py
yelp/obj/business.py
yelp/obj/business_response.py
yelp/obj/coordinate.py
yelp/obj/deal.py
yelp/obj/deal_option.py
yelp/obj/gift_certificate.py
yelp/obj/gift_certificate_option.py
yelp/obj/location.py
yelp/obj/region.py
yelp/obj/response_object.py
yelp/obj/review.py
yelp/obj/search_response.py
yelp/obj/span.py
yelp/obj/user.py
yelp-1.0.1.dist-info/DESCRIPTION.rst
yelp-1.0.1.dist-info/METADATA
yelp-1.0.1.dist-info/metadata.json
yelp-1.0.1.dist-info/RECORD
yelp-1.0.1.dist-info/top_level.txt
yelp-1.0.1.dist-info/WHEEL
