Metadata-Version: 2.0
Name: yelp
Version: 1.0.1
Summary: Python Clientlib for Yelp Public API
Home-page: https://github.com/Yelp/yelp-python
Author: Yelp
Author-email: partnerships@yelp.com
License: MIT
Keywords: yelp
Platform: UNKNOWN
Classifier: License :: OSI Approved :: MIT License
Classifier: Programming Language :: Python :: 2
Classifier: Programming Language :: Python :: 2.7
Classifier: Programming Language :: Python :: 3
Classifier: Programming Language :: Python :: 3.4
Classifier: Programming Language :: Python :: Implementation :: CPython
Requires-Dist: httplib2
Requires-Dist: oauth2
Requires-Dist: six
